{
    "PHD_American": {
        "tests": [], 
        "weights": [
            [
                [
                    0.19718089836511765, 
                    -0.15945023133407707, 
                    0.11980988413590227, 
                    0.04910333202780642, 
                    -0.17136876892476788, 
                    -0.1067183768200397, 
                    -0.16433796759838573, 
                    0.17822236180121281
                ], 
                [
                    -0.00820671498646125, 
                    0.09891280882659897, 
                    0.19734805899341323, 
                    0.01681215692486182, 
                    0.09868667100305512, 
                    -0.14959061105862564, 
                    -0.06425040960760939, 
                    -0.1824814698143488
                ], 
                [
                    -0.09893523563725122, 
                    0.12566551337020798, 
                    0.09336971422594675, 
                    -0.1876368399066732, 
                    0.06426811404423127, 
                    0.05383620134279388, 
                    -0.18468330585044732, 
                    -0.16074869209883202
                ], 
                [
                    -0.13678654995341039, 
                    0.09304022980476973, 
                    0.053242087331756616, 
                    0.04545778087336361, 
                    0.19497097551871406, 
                    0.10719936144719211, 
                    0.013354121468491631, 
                    -0.0024142462661373987
                ], 
                [
                    0.08600915600149917, 
                    0.07959568457303051, 
                    -0.03933457962994019, 
                    -0.026503593047230767, 
                    -0.03941622450105667, 
                    -0.19202463528992483, 
                    0.16302474484952378, 
                    -0.09573118643093377
                ], 
                [
                    0.07516207089459431, 
                    0.07936876649334695, 
                    -0.1670343411983867, 
                    0.19253221428208417, 
                    -0.06356796312278776, 
                    0.1740737566597692, 
                    0.12360344879777052, 
                    -0.06215862691139945
                ], 
                [
                    -0.039008506894676304, 
                    0.05034336990594124, 
                    0.19803614559574623, 
                    -0.10542397153880359, 
                    -0.14226536047577062, 
                    0.0155257557924946, 
                    -0.14458788923864066, 
                    -0.1626734967012481
                ]
            ], 
            [
                [
                    -0.16590914325481354, 
                    0.1110968015179129, 
                    0.19333496098329606, 
                    0.08982954434890922, 
                    0.08362344473271738
                ], 
                [
                    -0.13543084850977766, 
                    0.08762295936859549, 
                    -0.1779516754622985, 
                    -0.06212203081791509, 
                    0.15657556787354604
                ], 
                [
                    -0.15312767607133024, 
                    0.01613084500345105, 
                    0.17364045395459166, 
                    0.08603585203002967, 
                    -0.13507624547647656
                ], 
                [
                    0.07721179350383511, 
                    -0.07518194514434998, 
                    0.09792329417489792, 
                    0.12042124347533528, 
                    0.10786716225142817
                ], 
                [
                    -0.14962378233004464, 
                    0.02778986712321077, 
                    -0.15288472224639285, 
                    -0.1739343342901356, 
                    -0.08130448471007563
                ], 
                [
                    -0.18251988373596212, 
                    0.006721358651299247, 
                    0.022083488753430774, 
                    -0.09531209840729692, 
                    -0.021699775432429957
                ], 
                [
                    0.036176185881503675, 
                    0.06847102956250856, 
                    -0.1282233855190545, 
                    -0.1648818416407592, 
                    -0.09682748441667505
                ], 
                [
                    -0.1986771791637681, 
                    0.11411450393984685, 
                    0.12422113556814224, 
                    0.1666331298790823, 
                    0.08269565923488237
                ]
            ], 
            [
                [
                    0.13296118092672676, 
                    -0.06956278269306079, 
                    0.1375294681556108
                ], 
                [
                    0.08833141457024091, 
                    0.1760237595422245, 
                    -0.1882121122495947
                ], 
                [
                    -0.03281730721039633, 
                    -0.1377342243200318, 
                    0.048042002493035696
                ], 
                [
                    -0.08981623771166075, 
                    -0.17661171106276963, 
                    -0.006236334917437164
                ], 
                [
                    -0.034125315560609965, 
                    -0.16396701907257027, 
                    0.06011046525784186
                ]
            ], 
            [
                [
                    0.1760715120128068
                ], 
                [
                    -0.005885723411367255
                ], 
                [
                    -0.11377606546878948
                ]
            ]
        ], 
        "minimax": {
            "status": {
                "max": 0, 
                "min": 0
            }, 
            "gre_quant": {
                "max": 0, 
                "min": 0
            }, 
            "gre_writing": {
                "max": 0, 
                "min": 0
            }, 
            "decision": {
                "max": 0, 
                "min": 0
            }, 
            "ms_phd": {
                "max": 0, 
                "min": 0
            }, 
            "gpa": {
                "max": 0, 
                "min": 0
            }, 
            "gre_verbal": {
                "max": 0, 
                "min": 0
            }
        }
    }, 
    "MS_American": {
        "tests": [], 
        "weights": [
            [
                [
                    -0.0365101836062634, 
                    0.016184657804064306, 
                    0.0824102999122523, 
                    -0.18404499255742546, 
                    -0.0750052311341988, 
                    -0.035125504396087914, 
                    0.0925523656799711, 
                    -0.13735085592252844
                ], 
                [
                    -0.07705514864836555, 
                    0.056995768895510834, 
                    0.07530172228160581, 
                    0.10924172838248952, 
                    0.13515299119849322, 
                    0.1856203295005308, 
                    -0.13091117055967633, 
                    -0.001862646069777707
                ], 
                [
                    -0.09403211156059155, 
                    -0.15640076973499617, 
                    -0.11498663789234809, 
                    0.11428041330543243, 
                    -0.13760603251027753, 
                    -0.07541721879628419, 
                    -0.14642426044553952, 
                    0.1864747702098099
                ], 
                [
                    -0.19679882583443256, 
                    -0.02393858822208239, 
                    -0.10413703066938203, 
                    0.1471163651063781, 
                    0.11626321595843991, 
                    -0.00869163801697076, 
                    -0.0030378141333036734, 
                    -0.19391234791409026
                ], 
                [
                    -0.08092784986282134, 
                    0.10700912070344482, 
                    0.05841376734759174, 
                    -0.04127917786838514, 
                    0.12269927238185763, 
                    0.08604056358398765, 
                    -0.028077213818369084, 
                    0.060460675350407
                ], 
                [
                    -0.14101360858598655, 
                    0.04963066820685191, 
                    -0.019599603691403733, 
                    -0.10435460953465095, 
                    -0.1827842979402896, 
                    -0.19861913064376233, 
                    -0.09022754965479232, 
                    0.07410329336706578
                ], 
                [
                    -0.05491038037095458, 
                    0.17852303504358374, 
                    0.04076146175054535, 
                    -0.048950081543717106, 
                    -0.016137965759730838, 
                    0.14289529617671537, 
                    -0.1493690269472886, 
                    0.14528445449590283
                ]
            ], 
            [
                [
                    -0.09290044730394356, 
                    -0.10982902903352826, 
                    -0.1277282816644456, 
                    0.10942956422835909, 
                    -0.029589230047286724
                ], 
                [
                    -0.064962706180278, 
                    0.13698142438904543, 
                    -0.09782634662443429, 
                    -0.12185289167965255, 
                    -0.07960615679263645
                ], 
                [
                    0.16021611715516937, 
                    0.06112202449074777, 
                    -0.06420974713562586, 
                    0.18371739325559794, 
                    0.07409744449111105
                ], 
                [
                    -0.05924846841087503, 
                    -0.026588646179448283, 
                    0.18636582072701763, 
                    0.19923993904895704, 
                    -0.19561905957301495
                ], 
                [
                    -0.019646502116686365, 
                    -0.15643173509338523, 
                    -0.044428324727771334, 
                    0.02151329428525567, 
                    0.14674323229975156
                ], 
                [
                    -0.11754026566885822, 
                    -0.18780774448974494, 
                    -0.19094838508125248, 
                    -0.15408487931209677, 
                    0.09285158731248555
                ], 
                [
                    0.18764327177990675, 
                    0.06473180870517958, 
                    -0.13058998608699357, 
                    0.12311913429451243, 
                    0.17946143329383774
                ], 
                [
                    0.1604111908111439, 
                    -0.08363689111652582, 
                    -0.11393364990524645, 
                    0.18162086088545076, 
                    -0.1881340447694181
                ]
            ], 
            [
                [
                    0.1839781448042896, 
                    0.16075233546765944, 
                    -0.0021723910163214677
                ], 
                [
                    0.11377452854705372, 
                    0.06674928043807349, 
                    -0.08192055259066122
                ], 
                [
                    0.16499975599315897, 
                    0.0716420124647218, 
                    -0.1827537931233188
                ], 
                [
                    -0.1238700368729988, 
                    -0.19253449937974876, 
                    0.02914664314972515
                ], 
                [
                    -0.0154950701946662, 
                    0.10665854645465112, 
                    0.02994256276212562
                ]
            ], 
            [
                [
                    0.147001672900003
                ], 
                [
                    0.13055519342601363
                ], 
                [
                    -0.0631096381811081
                ]
            ]
        ], 
        "minimax": {
            "status": {
                "max": 0, 
                "min": 0
            }, 
            "gre_quant": {
                "max": 0, 
                "min": 0
            }, 
            "gre_writing": {
                "max": 0, 
                "min": 0
            }, 
            "decision": {
                "max": 0, 
                "min": 0
            }, 
            "ms_phd": {
                "max": 0, 
                "min": 0
            }, 
            "gpa": {
                "max": 0, 
                "min": 0
            }, 
            "gre_verbal": {
                "max": 0, 
                "min": 0
            }
        }
    }, 
    "PHD_AllStatus": {
        "tests": [], 
        "weights": [
            [
                [
                    -0.05618282447079645, 
                    0.01968759476586479, 
                    -0.05438247224483522, 
                    -0.17440988370940966, 
                    -0.06472198004257787, 
                    -0.14597568370059558, 
                    0.06934916182239587, 
                    0.15864950608751305
                ], 
                [
                    0.19032620456986066, 
                    0.1403340230530306, 
                    0.18622051141706575, 
                    -0.10651292507682825, 
                    0.050479936148310534, 
                    0.021934530395867652, 
                    0.08216588029960742, 
                    0.07239587318511875
                ], 
                [
                    -0.07516198771211742, 
                    -0.08678745765527945, 
                    0.008579764110843158, 
                    0.17785319504537994, 
                    0.07086740297225946, 
                    -0.1171549307494813, 
                    0.11839652596001116, 
                    0.10602982739740735
                ], 
                [
                    0.13294451460068513, 
                    0.03062186028383493, 
                    -0.10030201566932453, 
                    0.05227871500539266, 
                    -0.10231372020627805, 
                    0.14158392738790565, 
                    0.11765202100497657, 
                    0.14977747431444505
                ], 
                [
                    0.12489019100883997, 
                    -0.17040921366901907, 
                    0.18282947230895025, 
                    -0.12255816418546153, 
                    0.16103040383157485, 
                    0.034560339902672155, 
                    0.16736354072720394, 
                    0.027881106620827018
                ], 
                [
                    -0.179596802920246, 
                    -0.11402731495128081, 
                    -0.19572981656350313, 
                    0.047652381126172816, 
                    0.056100464640053804, 
                    -0.0334703393925245, 
                    0.07263441020506434, 
                    -0.07652145470813104
                ], 
                [
                    -0.1969478712405119, 
                    -0.12024566258351405, 
                    -0.13090196296336365, 
                    0.16174255305133406, 
                    0.040204109840773106, 
                    0.010672797030107428, 
                    -0.024301901110518775, 
                    -0.15149909208100884
                ]
            ], 
            [
                [
                    0.025921616935822595, 
                    0.05929481672513914, 
                    -0.0292026438082241, 
                    0.12516880884339437, 
                    -0.07401218096622583
                ], 
                [
                    -0.03476624387151811, 
                    -0.14136086134573864, 
                    0.05510591116347968, 
                    -0.017515398884780098, 
                    -0.17866715506572994
                ], 
                [
                    -0.09744314830036944, 
                    -0.04434118131381734, 
                    0.023820523689992074, 
                    0.01727046405151128, 
                    -0.17975575811084488
                ], 
                [
                    0.11069839426260647, 
                    -0.09940939630481754, 
                    0.16144830919861114, 
                    -0.19639140942260946, 
                    0.12711842916222676
                ], 
                [
                    0.08823146449884567, 
                    0.18465035348140724, 
                    -0.15992346960893222, 
                    -0.08789466998250149, 
                    0.031178242165854936
                ], 
                [
                    -0.08198276166132606, 
                    -0.10322992606092934, 
                    0.006686399464062548, 
                    0.13414417117135508, 
                    0.08516316471941837
                ], 
                [
                    -0.15227435093599714, 
                    -0.06476655260004405, 
                    0.03990274855981357, 
                    0.13691212279157922, 
                    -0.04447973232467453
                ], 
                [
                    -0.023215689344349588, 
                    -0.09662291982275897, 
                    -0.049446058837806645, 
                    0.07298185792537365, 
                    -0.1518721606203038
                ]
            ], 
            [
                [
                    0.14001034002568885, 
                    -0.04108204193333598, 
                    -0.13381412010121607
                ], 
                [
                    -0.15830393557201453, 
                    -0.11528896816599868, 
                    -0.12412506958984082
                ], 
                [
                    -0.0716353235648736, 
                    -0.15080128747633648, 
                    0.021214506858903054
                ], 
                [
                    0.08499797647342733, 
                    -0.017726155930542553, 
                    -0.08836742694611299
                ], 
                [
                    0.1419974398865344, 
                    0.18226470047683418, 
                    -0.06455665347773137
                ]
            ], 
            [
                [
                    -0.1277940015529908
                ], 
                [
                    0.016165417083604028
                ], 
                [
                    -0.008180407212195873
                ]
            ]
        ], 
        "minimax": {
            "status": {
                "max": 0, 
                "min": 0
            }, 
            "gre_quant": {
                "max": 0, 
                "min": 0
            }, 
            "gre_writing": {
                "max": 0, 
                "min": 0
            }, 
            "decision": {
                "max": 0, 
                "min": 0
            }, 
            "ms_phd": {
                "max": 0, 
                "min": 0
            }, 
            "gpa": {
                "max": 0, 
                "min": 0
            }, 
            "gre_verbal": {
                "max": 0, 
                "min": 0
            }
        }
    }, 
    "MS_AllStatus": {
        "tests": [], 
        "weights": [
            [
                [
                    -0.007212683399506814, 
                    0.1464091735524775, 
                    0.15495826139523372, 
                    0.1205153586618401, 
                    0.10210065233278137, 
                    -0.0024320428765660096, 
                    -0.12574250811085302, 
                    0.152297393611743
                ], 
                [
                    -0.08834902584471745, 
                    0.07235611748627047, 
                    -0.0531166704826945, 
                    -0.14154657734257317, 
                    0.02524588655463092, 
                    -0.08808678574035463, 
                    0.14671733128965542, 
                    -0.10130459689549323
                ], 
                [
                    -0.1022559811790833, 
                    0.017654830595073057, 
                    -0.07189152362113091, 
                    -0.10068533348968361, 
                    0.13541853487888744, 
                    0.03279959524821524, 
                    0.18155206898742615, 
                    -0.050232568786931886
                ], 
                [
                    0.08806421450921331, 
                    -0.057112033240838994, 
                    -0.054341810182541084, 
                    0.09311513932719889, 
                    -0.15611355466566082, 
                    0.18265221040932117, 
                    -0.09613577469706974, 
                    -0.16163178353634203
                ], 
                [
                    0.19271133487028724, 
                    -0.17335363058594422, 
                    -0.09217651262049023, 
                    0.06672455484895179, 
                    -0.17212525444157914, 
                    -0.18613415543149459, 
                    -0.11193661872986134, 
                    -0.05406745142905614
                ], 
                [
                    0.04496694559814168, 
                    0.08949537782607192, 
                    0.12204806930502471, 
                    -0.05951859533125867, 
                    0.0342679243597217, 
                    0.039582296676135276, 
                    -0.07089921862551993, 
                    0.10138971137070585
                ], 
                [
                    0.1980320598320045, 
                    0.11577783990553908, 
                    0.07039601905137888, 
                    0.08001406066408129, 
                    -0.11985282499611936, 
                    0.031159563112871658, 
                    0.021652455388611574, 
                    -0.03116692264624707
                ]
            ], 
            [
                [
                    -0.14417227728947443, 
                    0.19930851375082476, 
                    0.004260576015726214, 
                    -0.09557927597767964, 
                    0.04033377843435387
                ], 
                [
                    0.14929106428699412, 
                    0.17970532669225697, 
                    -0.040407708880590004, 
                    -0.036757589130855084, 
                    0.006743951059998338
                ], 
                [
                    0.0035189791618828736, 
                    0.17248596400358218, 
                    -0.017179293784396477, 
                    -0.1289184795437348, 
                    -0.04841105431563872
                ], 
                [
                    -0.04263725809242089, 
                    0.19870114089677748, 
                    -0.1314642697182004, 
                    0.11988462281616602, 
                    0.1199363618087892
                ], 
                [
                    -0.11231930360021206, 
                    -0.03762933458709122, 
                    -0.18278865806065958, 
                    -0.010051933413448622, 
                    -0.011294694258510901
                ], 
                [
                    0.06260189957295265, 
                    0.035877346147082934, 
                    -0.07351740862466438, 
                    -0.12272073467730715, 
                    -0.11701377084813164
                ], 
                [
                    0.10397937362773668, 
                    -0.06286893358600051, 
                    0.1496132160993977, 
                    -0.10598239569590105, 
                    0.1047617056838267
                ], 
                [
                    -0.13328212474386786, 
                    0.1438409207206312, 
                    0.10803727296306803, 
                    -0.05672074807187949, 
                    -0.16051333633807832
                ]
            ], 
            [
                [
                    0.014260906244222882, 
                    0.19205879489608207, 
                    -0.1558077070571572
                ], 
                [
                    0.022796601900135022, 
                    0.1076596699306665, 
                    -0.13391729830793636
                ], 
                [
                    -0.05416839450481309, 
                    0.043939660768128774, 
                    -0.19289727477563542
                ], 
                [
                    -0.01691393001817504, 
                    -0.004699001335913666, 
                    -0.11634530035865885
                ], 
                [
                    -0.07477660841736541, 
                    0.11732368861788767, 
                    -0.1150780714676301
                ]
            ], 
            [
                [
                    0.03665546972718983
                ], 
                [
                    -0.10891175938165026
                ], 
                [
                    0.04587047320300161
                ]
            ]
        ], 
        "minimax": {
            "status": {
                "max": 0, 
                "min": 0
            }, 
            "gre_quant": {
                "max": 0, 
                "min": 0
            }, 
            "gre_writing": {
                "max": 0, 
                "min": 0
            }, 
            "decision": {
                "max": 0, 
                "min": 0
            }, 
            "ms_phd": {
                "max": 0, 
                "min": 0
            }, 
            "gpa": {
                "max": 0, 
                "min": 0
            }, 
            "gre_verbal": {
                "max": 0, 
                "min": 0
            }
        }
    }, 
    "MS/PHD_American": {
        "tests": [], 
        "weights": [
            [
                [
                    0.08277301614397437, 
                    -0.05571937265547003, 
                    0.010867575189095258, 
                    -0.1795260375612415, 
                    -0.09139321025138761, 
                    -0.15837530703385605, 
                    -0.11774513055668732, 
                    -0.13524264425504756
                ], 
                [
                    0.010479028644597127, 
                    0.10396471039980615, 
                    -0.17639606489685106, 
                    0.06629181389676081, 
                    0.15843523606947013, 
                    0.17106969622686102, 
                    -0.005611742079854487, 
                    0.11805068315326878
                ], 
                [
                    0.16044629612831907, 
                    0.05170931584930638, 
                    -0.0914882232228481, 
                    -0.05410946453531587, 
                    -0.018113292325612484, 
                    0.19808380996506897, 
                    -0.00034413579518507986, 
                    0.1146046376035979
                ], 
                [
                    0.16198170099485298, 
                    0.1752374835086707, 
                    0.14359561565583528, 
                    -0.10875235945730868, 
                    0.13247521686230507, 
                    -0.06237224264145308, 
                    -0.10926165252275158, 
                    -0.056685885298965566
                ], 
                [
                    -0.18332350162801508, 
                    0.1589541085933125, 
                    -0.13126459050070516, 
                    0.030615665270881637, 
                    -0.023832553844852722, 
                    -0.16622380345276344, 
                    -0.0054058792549468715, 
                    0.11111868789607499
                ], 
                [
                    -0.04414478230467736, 
                    0.15518262264271387, 
                    -0.15271607669950674, 
                    0.08380023121116592, 
                    -0.16983754860954905, 
                    -0.07899351341129748, 
                    -0.1118191014416628, 
                    -0.16943052380491896
                ], 
                [
                    0.1106711015758472, 
                    -0.06989232519128216, 
                    -0.06873583761329663, 
                    -0.18592059356032287, 
                    -0.18670661947378053, 
                    -0.17925953369873984, 
                    0.058000893961271616, 
                    0.09407608270895501
                ]
            ], 
            [
                [
                    0.19791877671842178, 
                    -0.028673212053013236, 
                    0.17384052733588023, 
                    0.04531190458176412, 
                    0.15192919460452264
                ], 
                [
                    -0.11033211969378263, 
                    -0.17826894847358168, 
                    -0.017132834645622458, 
                    -0.07215551554392105, 
                    -0.19378367432130378
                ], 
                [
                    0.1425249554114173, 
                    -0.17936215990373505, 
                    -0.09103705504002613, 
                    0.08993059483720128, 
                    0.006455142644944095
                ], 
                [
                    0.0381499790167672, 
                    -0.18997715379260374, 
                    -0.0826556456299477, 
                    -0.1775283054260203, 
                    -0.005570166096952572
                ], 
                [
                    0.13378360163087016, 
                    -0.06012742241417701, 
                    0.09272621390588365, 
                    -0.08665164242922363, 
                    0.006163553940803507
                ], 
                [
                    0.17341993532687566, 
                    0.1175752011453331, 
                    0.07010571882287364, 
                    -0.1131577223716893, 
                    -0.11968831090968766
                ], 
                [
                    0.18587075398309733, 
                    -0.07334313436206474, 
                    0.0965255707737897, 
                    0.10909785826060969, 
                    0.1389048072653879
                ], 
                [
                    -0.0421239506831273, 
                    0.012938213585635211, 
                    -0.05728152371911724, 
                    -0.1900042360770506, 
                    -0.058451015411355556
                ]
            ], 
            [
                [
                    0.1316283731497902, 
                    -0.186513830573035, 
                    -0.0852323837383112
                ], 
                [
                    -0.043371781580335084, 
                    -0.1590392141048497, 
                    0.15250477263308043
                ], 
                [
                    0.1909813281929013, 
                    -0.10538447608879493, 
                    -0.11260077001835356
                ], 
                [
                    -0.0527010618409888, 
                    -0.06329263893891307, 
                    0.11601409150391129
                ], 
                [
                    -0.1313918412711343, 
                    -0.12530489627580393, 
                    -0.06081896621854846
                ]
            ], 
            [
                [
                    0.16178838376377436
                ], 
                [
                    0.06466336919069071
                ], 
                [
                    -0.01594063983574298
                ]
            ]
        ], 
        "minimax": {
            "status": {
                "max": 0, 
                "min": 0
            }, 
            "gre_quant": {
                "max": 0, 
                "min": 0
            }, 
            "gre_writing": {
                "max": 0, 
                "min": 0
            }, 
            "decision": {
                "max": 0, 
                "min": 0
            }, 
            "ms_phd": {
                "max": 0, 
                "min": 0
            }, 
            "gpa": {
                "max": 0, 
                "min": 0
            }, 
            "gre_verbal": {
                "max": 0, 
                "min": 0
            }
        }
    }, 
    "MS/PHD_AllStatus": {
        "tests": [], 
        "weights": [
            [
                [
                    -0.17570878542472781, 
                    -0.16121113677420387, 
                    0.15762331032300275, 
                    -0.19573339347219304, 
                    0.1899739862632563, 
                    -0.004521020394981257, 
                    -0.08790802827825202, 
                    0.08384374415480123
                ], 
                [
                    -0.19287996670252183, 
                    0.02503634066420335, 
                    0.07705848262431514, 
                    0.16795975631788035, 
                    -0.07586860281181514, 
                    0.03324022970129184, 
                    0.1204530773679448, 
                    -0.08009618105344277
                ], 
                [
                    -0.12057569491743636, 
                    0.041915399894032396, 
                    0.12435039605232423, 
                    -0.16569968648634423, 
                    0.06968932740851674, 
                    -0.03696091122618633, 
                    0.12144093311891652, 
                    -0.18035573749716316
                ], 
                [
                    -0.16411148159651434, 
                    0.1823736500512289, 
                    0.02699066907354758, 
                    -0.07721428349046851, 
                    -0.17275415614246362, 
                    -0.12146515838814675, 
                    -0.05734461235281191, 
                    -0.16285862463257417
                ], 
                [
                    -0.16160607548803432, 
                    -0.14355506632252985, 
                    0.038686206687903374, 
                    -1.9319131078970875e-05, 
                    0.1135673888026818, 
                    -0.029775752142688072, 
                    -0.08516381225123278, 
                    0.11806455256785969
                ], 
                [
                    0.03957563733741298, 
                    -0.16626209914005866, 
                    0.17119230298215943, 
                    -0.046783435845721755, 
                    0.14597768696950542, 
                    0.08356586363073881, 
                    -0.12856124852040854, 
                    0.1589183390815474
                ], 
                [
                    -0.18793266628908387, 
                    -0.007177650094466692, 
                    0.052609279784618324, 
                    -0.0963512428837782, 
                    0.1441066301912648, 
                    -0.16474224502847587, 
                    0.12181079834074998, 
                    0.1952307688099934
                ]
            ], 
            [
                [
                    -0.14988245733395122, 
                    0.10154543641468966, 
                    0.09737071098545341, 
                    -0.035091670361677485, 
                    -0.044827281459276114
                ], 
                [
                    -0.10764985991790939, 
                    -0.17473559071694988, 
                    -0.10191706774485981, 
                    0.17975962111802873, 
                    -0.11102437202057068
                ], 
                [
                    -0.1803709370183397, 
                    -0.14622470998271045, 
                    -0.028436754181939167, 
                    0.06068191358316177, 
                    -0.15735706956523343
                ], 
                [
                    0.13632894741207724, 
                    -0.07608083431369068, 
                    -0.10512506816961663, 
                    -0.07651527833840294, 
                    0.1531793881633552
                ], 
                [
                    -0.120641051587139, 
                    0.04651509941816484, 
                    0.07729801924830382, 
                    -0.11377840075394824, 
                    0.09527498128968853
                ], 
                [
                    0.1648234204259706, 
                    0.041930093359737464, 
                    0.15506869180073785, 
                    0.056570985288978304, 
                    0.07989973054168631
                ], 
                [
                    -0.01604708530737567, 
                    -0.09222843922613638, 
                    0.054040801989791, 
                    0.15933924713574105, 
                    -0.17103751746487378
                ], 
                [
                    -0.08073980120525603, 
                    -0.1388181008404928, 
                    -0.003876631237324707, 
                    -0.040555602521664014, 
                    0.07926481264573104
                ]
            ], 
            [
                [
                    -0.12070807811300482, 
                    0.14046301522797372, 
                    0.06577170563061252
                ], 
                [
                    0.08447899763914185, 
                    0.07659110859579238, 
                    -0.008762621788804964
                ], 
                [
                    0.0947517817999286, 
                    -0.1469571035982732, 
                    -0.17191512725617497
                ], 
                [
                    -0.0854356241439413, 
                    -0.1564994684272243, 
                    0.16655136781146823
                ], 
                [
                    -0.06388574910454975, 
                    0.0988496441968611, 
                    0.009752175379125344
                ]
            ], 
            [
                [
                    -0.12816153397376406
                ], 
                [
                    0.06884111255440556
                ], 
                [
                    0.18992117265123615
                ]
            ]
        ], 
        "minimax": {
            "status": {
                "max": 0, 
                "min": 0
            }, 
            "gre_quant": {
                "max": 0, 
                "min": 0
            }, 
            "gre_writing": {
                "max": 0, 
                "min": 0
            }, 
            "decision": {
                "max": 0, 
                "min": 0
            }, 
            "ms_phd": {
                "max": 0, 
                "min": 0
            }, 
            "gpa": {
                "max": 0, 
                "min": 0
            }, 
            "gre_verbal": {
                "max": 0, 
                "min": 0
            }
        }
    }
}